LICENSE
README.rst
setup.py
yiwheel/__init__.py
yiwheel/frame_helper.py
yiwheel/taos_helper.py
yiwheel/tools.py
yiwheel/yipkl.py
yiwheel.egg-info/PKG-INFO
yiwheel.egg-info/SOURCES.txt
yiwheel.egg-info/dependency_links.txt
yiwheel.egg-info/top_level.txt